{
  "_comment": "Generated by network.sh CBDC setup command",
  "_generated_time": "2025-06-27 20:20:21",
  "_network_type": "CBDC",
  "_central_bank": "PBOC",
  "_warning": "Do not edit this file manually. Use 'network.sh setup' to regenerate.",
  "network": {
    "channel_name": "cbdc-channel",
    "orderer": {
      "name": "OrdererOrg",
      "msp_id": "OrdererMSP",
      "domain": "example.com",
      "port": 7050,
      "operations_port": 9443
    },
    "organizations": [
      {
        "name": "PBOC",
        "msp_id": "PBOCMSP",
        "domain": "pboc.example.com",
        "type": "central_bank",
        "peer": {
          "port": 7051,
          "operations_port": 9444,
          "couchdb_port": 5984
        }
      }
,
      {
        "name": "ICBC",
        "msp_id": "ICBCMSP",
        "domain": "icbc.example.com",
        "type": "commercial_bank",
        "peer": {
          "port": 8051,
          "operations_port": 9445,
          "couchdb_port": 6984
        }
      }
,
      {
        "name": "ABC",
        "msp_id": "ABCMSP",
        "domain": "abc.example.com",
        "type": "commercial_bank",
        "peer": {
          "port": 9051,
          "operations_port": 9446,
          "couchdb_port": 7984
        }
      }
,
      {
        "name": "BOC",
        "msp_id": "BOCMSP",
        "domain": "boc.example.com",
        "type": "commercial_bank",
        "peer": {
          "port": 10051,
          "operations_port": 9447,
          "couchdb_port": 8984
        }
      }

    ]
  }
}
